someip_py/__init__.py
someip_py/client.py
someip_py/codec.py
someip_py/config.py
someip_py/constants.py
someip_py/frame.py
someip_py/interface.py
someip_py/scapy_extention.py
someip_py/secure_upload.py
someip_py/server.py
someip_py/utils.py
someip_py/service_interface/__init__.py
someip_py/service_interface/config.json
someip_py/service_interface/fields.json
someip_py/service_interface/V2x/__init__.py
someip_py/service_interface/V2x/ADAVPOperService/ADAVPOper.py
someip_py/service_interface/V2x/ADAVPOperService/__init__.py
someip_py/service_interface/V2x/ADCU_HmiService/ADParkingInfoPB.py
someip_py/service_interface/V2x/ADCU_HmiService/AVP3DMapInf.py
someip_py/service_interface/V2x/ADCU_HmiService/AVPCollectedDestinationCmdInf.py
someip_py/service_interface/V2x/ADCU_HmiService/AVPMapButtonCmdInf.py
someip_py/service_interface/V2x/ADCU_HmiService/AVPMapGenerateStatusInf.py
someip_py/service_interface/V2x/ADCU_HmiService/AVPMapInf.py
someip_py/service_interface/V2x/ADCU_HmiService/AVPMapListInfoInf.py
someip_py/service_interface/V2x/ADCU_HmiService/AVPMapManageCmdInf.py
someip_py/service_interface/V2x/ADCU_HmiService/AVPPopupInf.py
someip_py/service_interface/V2x/ADCU_HmiService/AbsoluteLocalizationInf.py
someip_py/service_interface/V2x/ADCU_HmiService/ActionableAreaInf.py
someip_py/service_interface/V2x/ADCU_HmiService/AdasMileageInf.py
someip_py/service_interface/V2x/ADCU_HmiService/AlarmInfoInf.py
someip_py/service_interface/V2x/ADCU_HmiService/AlignedSpeedSettingInf.py
someip_py/service_interface/V2x/ADCU_HmiService/ApaParkingStatusInf.py
someip_py/service_interface/V2x/ADCU_HmiService/ApaSlelectedSlotParkingmodeInf.py
someip_py/service_interface/V2x/ADCU_HmiService/AutoNaviSearchInf.py
someip_py/service_interface/V2x/ADCU_HmiService/AvoidJamAreaInf.py
someip_py/service_interface/V2x/ADCU_HmiService/AvpEgoPositionInMapInf.py
someip_py/service_interface/V2x/ADCU_HmiService/AvpTfRelToMapInf.py
someip_py-1.0.0.dist-info/METADATA
someip_py-1.0.0.dist-info/WHEEL
someip_py-1.0.0.dist-info/entry_points.txt
someip_py-1.0.0.dist-info/top_level.txt
someip_py-1.0.0.dist-info/RECORD
