Metadata-Version: 2.4
Name: someip-py
Version: 1.0.0
Summary: SOME/IP Libraries
Author: weidong.huang
Maintainer: weidong.huang
Maintainer-email: weidong.huang1229@gmail.com
Project-URL: Source, https://github.com/DeanHwd/someip-py
Keywords: SOME/IP
Platform: any
Classifier: Development Status :: 5 - Production/Stable
Classifier: Intended Audience :: Developers
Classifier: Operating System :: MacOS :: MacOS X
Classifier: Operating System :: Microsoft :: Windows
Classifier: Operating System :: POSIX
Classifier: Programming Language :: Python :: 3.7
Classifier: Programming Language :: Python :: 3.8
Classifier: Programming Language :: Python :: 3.9
Classifier: Programming Language :: Python :: 3.10
Classifier: Programming Language :: Python :: 3.11
Classifier: Programming Language :: Python :: 3.12
Classifier: Programming Language :: Python :: Implementation :: CPython
Classifier: Programming Language :: Python :: Implementation :: PyPy
Classifier: Topic :: Software Development :: Libraries
Classifier: Topic :: Software Development :: Testing
Classifier: Topic :: Utilities
Requires-Python: >=3.7
Requires-Dist: jinja2
Requires-Dist: openpyxl
Requires-Dist: pandas
Requires-Dist: protobuf<=3.20.3,>=3.18.0
Requires-Dist: scapy
Requires-Dist: setuptools
